spring_centralized_config_client/__init__.py
spring_centralized_config_client/client.py
spring_centralized_config_client-2.0.dist-info/LICENSE
spring_centralized_config_client-2.0.dist-info/METADATA
spring_centralized_config_client-2.0.dist-info/WHEEL
spring_centralized_config_client-2.0.dist-info/top_level.txt
spring_centralized_config_client-2.0.dist-info/RECORD
