Metadata-Version: 2.1
Name: spring_centralized_config_client
Version: 2.0
Summary: A library to fetch spring centralized config in decrypted flat format.
Author-email: Himanshu Verma <himanshu.v09@gmail.com>
Project-URL: Homepage, https://github.com/himanshuverma09/spring-centralized-config-client
Project-URL: Bug Tracker, https://github.com/himanshuverma09/spring-centralized-config-client/issues
Keywords: spring,config,client,centralized,decrypted
Classifier: Programming Language :: Python :: 3.6
Classifier: Programming Language :: Python :: 3.7
Classifier: Development Status :: 4 - Beta
Classifier: Intended Audience :: Developers
Classifier: License :: OSI Approved :: MIT License
Classifier: Operating System :: OS Independent
Classifier: Topic :: Software Development :: Libraries :: Java Libraries
Requires-Python: >=3
License-File: LICENSE
Requires-Dist: requests >=2.26.0
